{
  "id": "diyk_qa_0193c42d-5a39-760e-aca4-3a962fa8cf7a_d943fe7db9",
  "type": "qa",
  "title": "Cuma namazı en az kaç kişiyle kılınabilir?",
  "title_clean": "Cuma namazı en az kaç kişiyle kılınabilir?",
  "question": "Cuma namazı en az kaç kişiyle kılınabilir?",
  "question_clean": "Cuma namazı en az kaç kişiyle kılınabilir?",
  "answer_html": "<p>\tCuma namazının sahih olması için cemaatin şart olduğu konusunda bütün bilginler ittifak etmekle birlikte, gerekli görülen asgari sayının kaç olduğu hususunda farklı görüşler belirtmişlerdir.</p><p>\tCuma namazının kılınabilmesi için İmam Ebû Hanîfe’ye göre imamın dışında en az üç; İmam Ebû Yûsuf ve İmam Muhammed’e göre ise imamın dışında en az iki kişi bulunması gerekir. <sup>(İbnü’l-Hümâm, <em>Fethu’l-kadîr</em>, 2/60)</sup></p><p>\tHer ne kadar İmam Şâfiî kavli cedîdinde cuma namazının sahih olması için kırk kişinin bulunması şart koşulmuşsa da kavli kadiminde imam dâhil üç kişinin bulunması yeterli görülmüştür. Hanbelî mezhebine göre ise en az kırk kişi bulunmalıdır. <sup>(Nevevî, <em>el-Mecmu’,</em> 4/502; Zekeriya el-Ensârî, <em>el-Ğurer,</em> 2/8; İbn Kudâme, <em>el-Muğnî,</em> 2/242)</sup> Mâlikî mezhebine göre ise on iki kişinin bulunması şarttır. <sup>(Haraşî, <em>Şerhu Muhtasar,</em> 2/76-77)</sup></p><p>\tHz. Peygamber’in <sup>(s.a.s.)</sup> Medine’ye hicretinden önce Nakîu’l-Hadamat’ta kılınan cuma namazında kırk kişi hazır bulunmuştu. <sup>(İbn Mâce, İkâmetu’s-Salavât, 78 [1082])</sup> Ancak daha az kişi ile cuma namazı kılındığı da bilinmektedir. Nitekim Hz. Peygamber’in <sup>(s.a.s.)</sup> emri ile Mus’ab b. Umeyr Medine’de 12 kişiye cuma namazını kıldırmıştır. <sup>(Beyhakî, <em>es-Sünenü’l-kübrâ,</em> 3/255 [5617])</sup></p><p>\tResûlullah <sup>(s.a.s.)</sup>, cuma namazını kıldırırken, ticaret kervanının geldiğini haber alan cemaatten on iki kişi dışında hepsinin dışarı çıktığı rivâyeti de sahih hadis kaynaklarında yer almaktadır. <sup>(Buhârî, Cum'a, 38 [936])</sup> Öte yandan Hz. Peygamber bir yerleşim biriminde sadece dört kişi bulunsa bile, cuma namazının farz olduğunu bildirmiştir. <sup>(Beyhakî, <em>es-Sünenü’l-kübrâ,</em> 3/255 [5617])</sup></p><p>\tGörüldüğü üzere Hz. Peygamber’den <sup>(s.a.s.) </sup>&nbsp;gelen rivâyetler, biri imam olmak üzere en az dört kişinin bulunduğu yerde cuma namazının kılınabileceğini göstermektedir. Bu da cuma namazının kılınabilmesi için gerekli kişi sayısının alt sınırını belirler.</p><p></p> \n            <div>\n                \n            </div>",
  "answer_text": "Cuma namazının sahih olması için cemaatin şart olduğu konusunda bütün bilginler ittifak etmekle birlikte, gerekli görülen asgari sayının kaç olduğu hususunda farklı görüşler belirtmişlerdir. Cuma namazının kılınabilmesi için İmam Ebû Hanîfe'ye göre imamın dışında en az üç; İmam Ebû Yûsuf ve İmam Muhammed'e göre ise imamın dışında en az iki kişi bulunması gerekir. (İbnü'l-Hümâm, Fethu'l-kadîr, 2/60) Her ne kadar İmam Şâfiî kavli cedîdinde cuma namazının sahih olması için kırk kişinin bulunması şart koşulmuşsa da kavli kadiminde imam dâhil üç kişinin bulunması yeterli görülmüştür. Hanbelî mezhebine göre ise en az kırk kişi bulunmalıdır. (Nevevî, el-Mecmu', 4/502; Zekeriya el-Ensârî, el-Ğurer, 2/8; İbn Kudâme, el-Muğnî, 2/242) Mâlikî mezhebine göre ise on iki kişinin bulunması şarttır. (Haraşî, Şerhu Muhtasar, 2/76-77) Hz. Peygamber'in (s.a.s.) Medine'ye hicretinden önce Nakîu'l-Hadamat'ta kılınan cuma namazında kırk kişi hazır bulunmuştu. (İbn Mâce, İkâmetu's-Salavât, 78 [1082]) Ancak daha az kişi ile cuma namazı kılındığı da bilinmektedir. Nitekim Hz. Peygamber'in (s.a.s.) emri ile Mus'ab b. Umeyr Medine'de 12 kişiye cuma namazını kıldırmıştır. (Beyhakî, es-Sünenü'l-kübrâ, 3/255 [5617]) Resûlullah (s.a.s.), cuma namazını kıldırırken, ticaret kervanının geldiğini haber alan cemaatten on iki kişi dışında hepsinin dışarı çıktığı rivâyeti de sahih hadis kaynaklarında yer almaktadır. (Buhârî, Cum'a, 38 [936]) Öte yandan Hz. Peygamber bir yerleşim biriminde sadece dört kişi bulunsa bile, cuma namazının farz olduğunu bildirmiştir. (Beyhakî, es-Sünenü'l-kübrâ, 3/255 [5617]) Görüldüğü üzere Hz. Peygamber'den (s.a.s.) gelen rivâyetler, biri imam olmak üzere en az dört kişinin bulunduğu yerde cuma namazının kılınabileceğini göstermektedir. Bu da cuma namazının kılınabilmesi için gerekli kişi sayısının alt sınırını belirler.",
  "answer_text_clean": "Cuma namazının sahih olması için cemaatin şart olduğu konusunda bütün bilginler ittifak etmekle birlikte, gerekli görülen asgari sayının kaç olduğu hususunda farklı görüşler belirtmişlerdir. Cuma namazının kılınabilmesi için İmam Ebû Hanîfe'ye göre imamın dışında en az üç; İmam Ebû Yûsuf ve İmam Muhammed'e göre ise imamın dışında en az iki kişi bulunması gerekir. (İbnü'l-Hümâm, Fethu'l-kadîr, 2/60) Her ne kadar İmam Şâfiî kavli cedîdinde cuma namazının sahih olması için kırk kişinin bulunması şart koşulmuşsa da kavli kadiminde imam dâhil üç kişinin bulunması yeterli görülmüştür. Hanbelî mezhebine göre ise en az kırk kişi bulunmalıdır. (Nevevî, el-Mecmu', 4/502; Zekeriya el-Ensârî, el-Ğurer, 2/8; İbn Kudâme, el-Muğnî, 2/242) Mâlikî mezhebine göre ise on iki kişinin bulunması şarttır. (Haraşî, Şerhu Muhtasar, 2/76-77) Hz. Peygamber'in (s.a.s.) Medine'ye hicretinden önce Nakîu'l-Hadamat'ta kılınan cuma namazında kırk kişi hazır bulunmuştu. (İbn Mâce, İkâmetu's-Salavât, 78 [1082]) Ancak daha az kişi ile cuma namazı kılındığı da bilinmektedir. Nitekim Hz. Peygamber'in (s.a.s.) emri ile Mus'ab b. Umeyr Medine'de 12 kişiye cuma namazını kıldırmıştır. (Beyhakî, es-Sünenü'l-kübrâ, 3/255 [5617]) Resûlullah (s.a.s.), cuma namazını kıldırırken, ticaret kervanının geldiğini haber alan cemaatten on iki kişi dışında hepsinin dışarı çıktığı rivâyeti de sahih hadis kaynaklarında yer almaktadır. (Buhârî, Cum'a, 38 [936]) Öte yandan Hz. Peygamber bir yerleşim biriminde sadece dört kişi bulunsa bile, cuma namazının farz olduğunu bildirmiştir. (Beyhakî, es-Sünenü'l-kübrâ, 3/255 [5617]) Görüldüğü üzere Hz. Peygamber'den (s.a.s.) gelen rivâyetler, biri imam olmak üzere en az dört kişinin bulunduğu yerde cuma namazının kılınabileceğini göstermektedir. Bu da cuma namazının kılınabilmesi için gerekli kişi sayısının alt sınırını belirler.",
  "category_path": [
    "NAMAZ",
    "Cuma Namazı",
    "Cuma namazı en az kaç kişiyle kılınabilir?"
  ],
  "tags": [
    "NAMAZ",
    "Cuma Namazı",
    "Cuma namazı en az kaç kişiyle kılınabilir?",
    "cuma",
    "namazı",
    "kaç",
    "kişiyle"
  ],
  "source_name": "Din İşleri Yüksek Kurulu",
  "source_url": "https://kurul.diyanet.gov.tr/soru/cuma-namazi-en-az-kac-kisiyle-kilinabilir/0193c42d-5a39-760e-aca4-3a962fa8cf7a",
  "source_domain": "kurul.diyanet.gov.tr",
  "language": "tr",
  "is_official": true,
  "content_hash": "sha256:159228c100ef6e7b889b7d7ee08372736a1ab144fc4b989bc7cd73f11cce77fc",
  "search_keywords": [
    "cuma",
    "namazı",
    "kaç",
    "kişiyle",
    "kılınabilir",
    "namazının",
    "sahih",
    "olması",
    "cemaatin",
    "şart",
    "olduğu",
    "konusunda",
    "bütün",
    "bilginler",
    "ittifak",
    "etmekle",
    "birlikte",
    "gerekli",
    "görülen",
    "asgari",
    "sayının",
    "hususunda",
    "farklı",
    "görüşler",
    "belirtmişlerdir",
    "kılınabilmesi",
    "imam",
    "ebû",
    "hanîfe",
    "göre",
    "imamın",
    "dışında",
    "yûsuf",
    "muhammed",
    "iki",
    "kişi",
    "bulunması",
    "gerekir",
    "ibnü",
    "hümâm"
  ],
  "search_document": "Başlık: Cuma namazı en az kaç kişiyle kılınabilir? Soru: Cuma namazı en az kaç kişiyle kılınabilir? Cevap: Cuma namazının sahih olması için cemaatin şart olduğu konusunda bütün bilginler ittifak etmekle birlikte, gerekli görülen asgari sayının kaç olduğu hususunda farklı görüşler belirtmişlerdir. Cuma namazının kılınabilmesi için İmam Ebû Hanîfe'ye göre imamın dışında en az üç; İmam Ebû Yûsuf ve İmam Muhammed'e göre ise imamın dışında en az iki kişi bulunması gerekir. (İbnü'l-Hümâm, Fethu'l-kadîr, 2/60) Her ne kadar İmam Şâfiî kavli cedîdinde cuma namazının sahih olması için kırk kişinin bulunması şart koşulmuşsa da kavli kadiminde imam dâhil üç kişinin bulunması yeterli görülmüştür. Hanbelî mezhebine göre ise en az kırk kişi bulunmalıdır. (Nevevî, el-Mecmu', 4/502; Zekeriya el-Ensârî, el-Ğurer, 2/8; İbn Kudâme, el-Muğnî, 2/242) Mâlikî mezhebine göre ise on iki kişinin bulunması şarttır. (Haraşî, Şerhu Muhtasar, 2/76-77) Hz. Peygamber'in (s.a.s.) Medine'ye hicretinden önce Nakîu'l-Hadamat'ta kılınan cuma namazında kırk kişi hazır bulunmuştu. (İbn Mâce, İkâmetu's-Salavât, 78 [1082]) Ancak daha az kişi ile cuma namazı kılındığı da bilinmektedir. Nitekim Hz. Peygamber'in (s.a.s.) emri ile Mus'ab b. Umeyr Medine'de 12 kişiye cuma namazını kıldırmıştır. (Beyhakî, es-Sünenü'l-kübrâ, 3/255 [5617]) Resûlullah (s.a.s.), cuma namazını kıldırırken, ticaret kervanının geldiğini haber alan cemaatten on iki kişi dışında hepsinin dışarı çıktığı rivâyeti de sahih hadis kaynaklarında yer almaktadır. (Buhârî, Cum'a, 38 [936]) Öte yandan Hz. Peygamber bir yerleşim biriminde sadece dört kişi bulunsa bile, cuma namazının farz olduğunu bildirmiştir. (Beyhakî, es-Sünenü'l-kübrâ, 3/255 [5617]) Görüldüğü üzere Hz. Peygamber'den (s.a.s.) gelen rivâyetler, biri imam olmak üzere en az dört kişinin bulunduğu yerde cuma namazının kılınabileceğini göstermektedir. Bu da cuma namazının kılınabilmesi için gerekli kişi sayısının alt sınırını belirler. Kategori: NAMAZ > Cuma Namazı > Cuma namazı en az kaç kişiyle kılınabilir?",
  "discovered_at": "2026-03-16T23:41:03.085Z",
  "fetched_at": "2026-03-17T00:08:03.786Z",
  "parsed_at": "2026-03-17T00:09:44.612Z",
  "canonical_identifier": "0193c42d-5a39-760e-aca4-3a962fa8cf7a",
  "low_confidence": false,
  "decision_kind": null,
  "decision_year": null,
  "decision_no": null,
  "subject": null
}
