{
  "id": "diyk_qa_719f8e10-4874-4e23-047d-08dd1c135351_4c4dcfccd2",
  "type": "qa",
  "title": "Dişi hayvanların kurban olarak kesilmesinin hükmü nedir?",
  "title_clean": "Dişi hayvanların kurban olarak kesilmesinin hükmü nedir?",
  "question": "Dişi hayvanların kurban olarak kesilmesinin hükmü nedir?",
  "question_clean": "Dişi hayvanların kurban olarak kesilmesinin hükmü nedir?",
  "answer_html": "<p>Malî ve sosyal nitelikleri bir arada bulunduran kurban ibadeti, Yüce Allah’a karşı olan teslimiyeti ve kulluğu ifade etmektedir. Toplumda birlik, kardeşlik, yardımlaşma ve dayanışma ruhunu diri tutan bu ibadetin çerçevesi, Kur’an-ı Kerim’in yanı sıra Hz. Peygamber’in (s.a.s.) söz ve uygulamalarıyla belirlenmiştir. Hz. Peygamber’in (s.a.s.) kurban ibadeti hususunda doğrudan veya dolaylı olarak açıklama mahiyetinde birçok söz ve uygulaması olmuştur. Bu söz ve uygulamalara bakıldığında deve, sığır gibi büyükbaş hayvanlarla, koyun, keçi gibi küçükbaş hayvanların belirli şartları taşımaları durumunda, erkek olsun dişi olsun kurban olarak kesildikleri görülmektedir. Ancak İslam âlimleri bu söz ve uygulamalar ışığında kurbanlık hayvanın kesiminde dişi ve erkek cinslerinden hangisinin daha faziletli olduğu hususunda farklı görüşler ortaya koymuşlardır.&nbsp;</p><p>Mâlikî ve Şafiî mezhebi âlimleri kurbanlık hayvanlarda genel olarak erkek cinsini dişi cinsine göre faziletli görmektedirler. Hanefî mezhebi âlimleri ise koyunda erkek; keçi, deve ve sığırda ise dişi cinslerinin daha faziletli olduğunu ifade etmişlerdir. Ancak her iki görüş sahiplerinin gerekçelerine bakıldığında bunda, yaşadıkları zamanın şartları/ihtiyaçları, hayvanın etinin fazlalığı, lezzeti ve kalitesi ile ilgili değerlendirmelerin ve bölgesel alışkanlıkların etkili olduğu görülmektedir. Nitekim kurbanlıklarda dişi hayvanların kesilmesinin daha faziletli olduğunu ifade eden görüş sahipleri, etinin daha fazla ve kaliteli olacağı gerekçesiyle gerek koyun cinsinden gerekse keçi cinsinden olsun burulmuş olan erkek hayvanın dişisinden daha faziletli olacağını dile getirmişlerdir. Yine kurbanlık hayvanlarda genel olarak erkek cinsinin tercih edilmesini faziletli kabul eden görüş sahipleri, birtakım sebeplerle erkek hayvanın etinin kalitesi düştüğü takdirde, hiç doğum yapmamış dişi hayvanın kurban edilmesinin daha faziletli olacağını belirtmişlerdir (Bkz. Kâsânî, Bedâi, V, 80; Ramlî, Nihâye, VIII, 133; Desukî, Haşiyetü’d-Desukî, II,121; İbn Âbidîn, Reddü’l-Muhtâr, VI, 322; Vehbe Zuhayli, Mevsuatü’lFıkhi’l-İslami ve’l-Kadâya’l-Mu’âsıra, III, 613).&nbsp;</p><p>Bütün bu görüşler delilleriyle birlikte değerlendirildiğinde bu meseleye genellikle içinde bulunulan şartlar, örf ve alışkanlıklar, etin çokluğu, lezzeti ve kalitesi bağlamında yaklaşıldığı, dolayısıyla konunun ictihadî bir mesele olduğu ortaya çıkmaktadır. Söz konusu bu görüşler, kurban ibadetinin özüyle ve onun değişmez esaslarıyla ilgili olmayıp, toplum menfaatini gözetme ve Yüce Allah’a en iyi hayvanı kurban etme hassasiyetinin bir sonucu olarak sâdır olmuştur.&nbsp;</p><p>Günümüzde de benzer bir bakış açısıyla farklı görüşlerin ortaya konulması ve farklı tedbirlerin alınması tabiidir. Nitekim benzer tedbirlerin Hz. Peygamber (s.a.s.) döneminde de alındığı görülmektedir. İbn Abbas’ın naklettiğine göre bir dönem develerin azalması üzerine Hz. Peygamber sahabilere sığır kesmelerini emretmişti. (İbn Mâce, “Edâhî” 5.) Hz. Peygamber’in&nbsp;</p><p>(s.a.s.) bu uygulaması, kurbanlık seçiminde, sosyo-ekonomik şartların, kurbanlık hayvanların sayısal ya da niteliksel olarak o andaki özel durumlarının dikkate alınması gerektiğini ve hayvancılık politikası açısından bazı tedbirlerin alınabileceğini göstermesi açısından önem arz etmektedir.&nbsp;</p><p>Sonuç olarak, kurbanlık hayvanın erkek veya dişi olması, kurbanın geçerlilik şartları arasında yer almamaktadır. Hangisinin kesiminin daha faziletli olduğu hususu ise içinde bulunulan şartlar/ihtiyaçlar, etin çokluğu, lezzeti ve kalitesi bağlamındaki yerleşik örf çerçevesinde tartışılmıştır. Dolayısıyla günümüzde de toplumun menfaati dikkate alınarak hayvan neslinin korunması, dişi hayvanların kurban edilmesinden kaynaklanan maddi kaybın önlenmesi gibi maslahatlar da gözetilerek dişi hayvanların kurban edilmesinin kısıtlanmasında dini bir sakınca bulunmamaktadır. Bu itibarla dişi hayvanların kurban edilmesinin hayvan üretimine zarar vermesi halinde, kurban kesiminde erkek hayvanların tercih edilmesi dinen de uygun olur.&nbsp;</p> \n            <div>\n                \n            </div>",
  "answer_text": "Malî ve sosyal nitelikleri bir arada bulunduran kurban ibadeti, Yüce Allah'a karşı olan teslimiyeti ve kulluğu ifade etmektedir. Toplumda birlik, kardeşlik, yardımlaşma ve dayanışma ruhunu diri tutan bu ibadetin çerçevesi, Kur'an-ı Kerim'in yanı sıra Hz. Peygamber'in (s.a.s.) söz ve uygulamalarıyla belirlenmiştir. Hz. Peygamber'in (s.a.s.) kurban ibadeti hususunda doğrudan veya dolaylı olarak açıklama mahiyetinde birçok söz ve uygulaması olmuştur. Bu söz ve uygulamalara bakıldığında deve, sığır gibi büyükbaş hayvanlarla, koyun, keçi gibi küçükbaş hayvanların belirli şartları taşımaları durumunda, erkek olsun dişi olsun kurban olarak kesildikleri görülmektedir. Ancak İslam âlimleri bu söz ve uygulamalar ışığında kurbanlık hayvanın kesiminde dişi ve erkek cinslerinden hangisinin daha faziletli olduğu hususunda farklı görüşler ortaya koymuşlardır. Mâlikî ve Şafiî mezhebi âlimleri kurbanlık hayvanlarda genel olarak erkek cinsini dişi cinsine göre faziletli görmektedirler. Hanefî mezhebi âlimleri ise koyunda erkek; keçi, deve ve sığırda ise dişi cinslerinin daha faziletli olduğunu ifade etmişlerdir. Ancak her iki görüş sahiplerinin gerekçelerine bakıldığında bunda, yaşadıkları zamanın şartları/ihtiyaçları, hayvanın etinin fazlalığı, lezzeti ve kalitesi ile ilgili değerlendirmelerin ve bölgesel alışkanlıkların etkili olduğu görülmektedir. Nitekim kurbanlıklarda dişi hayvanların kesilmesinin daha faziletli olduğunu ifade eden görüş sahipleri, etinin daha fazla ve kaliteli olacağı gerekçesiyle gerek koyun cinsinden gerekse keçi cinsinden olsun burulmuş olan erkek hayvanın dişisinden daha faziletli olacağını dile getirmişlerdir. Yine kurbanlık hayvanlarda genel olarak erkek cinsinin tercih edilmesini faziletli kabul eden görüş sahipleri, birtakım sebeplerle erkek hayvanın etinin kalitesi düştüğü takdirde, hiç doğum yapmamış dişi hayvanın kurban edilmesinin daha faziletli olacağını belirtmişlerdir (Bkz. Kâsânî, Bedâi, V, 80; Ramlî, Nihâye, VIII, 133; Desukî, Haşiyetü'd-Desukî, II,121; İbn Âbidîn, Reddü'l-Muhtâr, VI, 322; Vehbe Zuhayli, Mevsuatü'lFıkhi'l-İslami ve'l-Kadâya'l-Mu'âsıra, III, 613). Bütün bu görüşler delilleriyle birlikte değerlendirildiğinde bu meseleye genellikle içinde bulunulan şartlar, örf ve alışkanlıklar, etin çokluğu, lezzeti ve kalitesi bağlamında yaklaşıldığı, dolayısıyla konunun ictihadî bir mesele olduğu ortaya çıkmaktadır. Söz konusu bu görüşler, kurban ibadetinin özüyle ve onun değişmez esaslarıyla ilgili olmayıp, toplum menfaatini gözetme ve Yüce Allah'a en iyi hayvanı kurban etme hassasiyetinin bir sonucu olarak sâdır olmuştur. Günümüzde de benzer bir bakış açısıyla farklı görüşlerin ortaya konulması ve farklı tedbirlerin alınması tabiidir. Nitekim benzer tedbirlerin Hz. Peygamber (s.a.s.) döneminde de alındığı görülmektedir. İbn Abbas'ın naklettiğine göre bir dönem develerin azalması üzerine Hz. Peygamber sahabilere sığır kesmelerini emretmişti. (İbn Mâce, \"Edâhî\" 5.) Hz. Peygamber'in (s.a.s.) bu uygulaması, kurbanlık seçiminde, sosyo-ekonomik şartların, kurbanlık hayvanların sayısal ya da niteliksel olarak o andaki özel durumlarının dikkate alınması gerektiğini ve hayvancılık politikası açısından bazı tedbirlerin alınabileceğini göstermesi açısından önem arz etmektedir. Sonuç olarak, kurbanlık hayvanın erkek veya dişi olması, kurbanın geçerlilik şartları arasında yer almamaktadır. Hangisinin kesiminin daha faziletli olduğu hususu ise içinde bulunulan şartlar/ihtiyaçlar, etin çokluğu, lezzeti ve kalitesi bağlamındaki yerleşik örf çerçevesinde tartışılmıştır. Dolayısıyla günümüzde de toplumun menfaati dikkate alınarak hayvan neslinin korunması, dişi hayvanların kurban edilmesinden kaynaklanan maddi kaybın önlenmesi gibi maslahatlar da gözetilerek dişi hayvanların kurban edilmesinin kısıtlanmasında dini bir sakınca bulunmamaktadır. Bu itibarla dişi hayvanların kurban edilmesinin hayvan üretimine zarar vermesi halinde, kurban kesiminde erkek hayvanların tercih edilmesi dinen de uygun olur.",
  "answer_text_clean": "Malî ve sosyal nitelikleri bir arada bulunduran kurban ibadeti, Yüce Allah'a karşı olan teslimiyeti ve kulluğu ifade etmektedir. Toplumda birlik, kardeşlik, yardımlaşma ve dayanışma ruhunu diri tutan bu ibadetin çerçevesi, Kur'an-ı Kerim'in yanı sıra Hz. Peygamber'in (s.a.s.) söz ve uygulamalarıyla belirlenmiştir. Hz. Peygamber'in (s.a.s.) kurban ibadeti hususunda doğrudan veya dolaylı olarak açıklama mahiyetinde birçok söz ve uygulaması olmuştur. Bu söz ve uygulamalara bakıldığında deve, sığır gibi büyükbaş hayvanlarla, koyun, keçi gibi küçükbaş hayvanların belirli şartları taşımaları durumunda, erkek olsun dişi olsun kurban olarak kesildikleri görülmektedir. Ancak İslam âlimleri bu söz ve uygulamalar ışığında kurbanlık hayvanın kesiminde dişi ve erkek cinslerinden hangisinin daha faziletli olduğu hususunda farklı görüşler ortaya koymuşlardır. Mâlikî ve Şafiî mezhebi âlimleri kurbanlık hayvanlarda genel olarak erkek cinsini dişi cinsine göre faziletli görmektedirler. Hanefî mezhebi âlimleri ise koyunda erkek; keçi, deve ve sığırda ise dişi cinslerinin daha faziletli olduğunu ifade etmişlerdir. Ancak her iki görüş sahiplerinin gerekçelerine bakıldığında bunda, yaşadıkları zamanın şartları/ihtiyaçları, hayvanın etinin fazlalığı, lezzeti ve kalitesi ile ilgili değerlendirmelerin ve bölgesel alışkanlıkların etkili olduğu görülmektedir. Nitekim kurbanlıklarda dişi hayvanların kesilmesinin daha faziletli olduğunu ifade eden görüş sahipleri, etinin daha fazla ve kaliteli olacağı gerekçesiyle gerek koyun cinsinden gerekse keçi cinsinden olsun burulmuş olan erkek hayvanın dişisinden daha faziletli olacağını dile getirmişlerdir. Yine kurbanlık hayvanlarda genel olarak erkek cinsinin tercih edilmesini faziletli kabul eden görüş sahipleri, birtakım sebeplerle erkek hayvanın etinin kalitesi düştüğü takdirde, hiç doğum yapmamış dişi hayvanın kurban edilmesinin daha faziletli olacağını belirtmişlerdir (Bkz. Kâsânî, Bedâi, V, 80; Ramlî, Nihâye, VIII, 133; Desukî, Haşiyetü'd-Desukî, II,121; İbn Âbidîn, Reddü'l-Muhtâr, VI, 322; Vehbe Zuhayli, Mevsuatü'lFıkhi'l-İslami ve'l-Kadâya'l-Mu'âsıra, III, 613). Bütün bu görüşler delilleriyle birlikte değerlendirildiğinde bu meseleye genellikle içinde bulunulan şartlar, örf ve alışkanlıklar, etin çokluğu, lezzeti ve kalitesi bağlamında yaklaşıldığı, dolayısıyla konunun ictihadî bir mesele olduğu ortaya çıkmaktadır. Söz konusu bu görüşler, kurban ibadetinin özüyle ve onun değişmez esaslarıyla ilgili olmayıp, toplum menfaatini gözetme ve Yüce Allah'a en iyi hayvanı kurban etme hassasiyetinin bir sonucu olarak sâdır olmuştur. Günümüzde de benzer bir bakış açısıyla farklı görüşlerin ortaya konulması ve farklı tedbirlerin alınması tabiidir. Nitekim benzer tedbirlerin Hz. Peygamber (s.a.s.) döneminde de alındığı görülmektedir. İbn Abbas'ın naklettiğine göre bir dönem develerin azalması üzerine Hz. Peygamber sahabilere sığır kesmelerini emretmişti. (İbn Mâce, \"Edâhî\" 5.) Hz. Peygamber'in (s.a.s.) bu uygulaması, kurbanlık seçiminde, sosyo-ekonomik şartların, kurbanlık hayvanların sayısal ya da niteliksel olarak o andaki özel durumlarının dikkate alınması gerektiğini ve hayvancılık politikası açısından bazı tedbirlerin alınabileceğini göstermesi açısından önem arz etmektedir. Sonuç olarak, kurbanlık hayvanın erkek veya dişi olması, kurbanın geçerlilik şartları arasında yer almamaktadır. Hangisinin kesiminin daha faziletli olduğu hususu ise içinde bulunulan şartlar/ihtiyaçlar, etin çokluğu, lezzeti ve kalitesi bağlamındaki yerleşik örf çerçevesinde tartışılmıştır. Dolayısıyla günümüzde de toplumun menfaati dikkate alınarak hayvan neslinin korunması, dişi hayvanların kurban edilmesinden kaynaklanan maddi kaybın önlenmesi gibi maslahatlar da gözetilerek dişi hayvanların kurban edilmesinin kısıtlanmasında dini bir sakınca bulunmamaktadır. Bu itibarla dişi hayvanların kurban edilmesinin hayvan üretimine zarar vermesi halinde, kurban kesiminde erkek hayvanların tercih edilmesi dinen de uygun olur.",
  "category_path": [
    "KURBAN",
    "Kurban Kesmenin Hükmü ve Hikmetleri",
    "Dişi hayvanların kurban olarak kesilmesinin hükmü nedir?"
  ],
  "tags": [
    "KURBAN",
    "Kurban Kesmenin Hükmü ve Hikmetleri",
    "Dişi hayvanların kurban olarak kesilmesinin hükmü nedir?",
    "dişi",
    "hayvanların",
    "olarak"
  ],
  "source_name": "Din İşleri Yüksek Kurulu",
  "source_url": "https://kurul.diyanet.gov.tr/soru/disi-hayvanlarin-kurban-olarak-kesilmesinin-hukmu-nedir/719f8e10-4874-4e23-047d-08dd1c135351",
  "source_domain": "kurul.diyanet.gov.tr",
  "language": "tr",
  "is_official": true,
  "content_hash": "sha256:6108fdfe51d995da2d5c3c0ab337c0ce87a5c71b796bd82afdf05d4835d1cff3",
  "search_keywords": [
    "dişi",
    "hayvanların",
    "kurban",
    "olarak",
    "kesilmesinin",
    "hükmü",
    "nedir",
    "malî",
    "sosyal",
    "nitelikleri",
    "arada",
    "bulunduran",
    "ibadeti",
    "yüce",
    "allah",
    "karşı",
    "olan",
    "teslimiyeti",
    "kulluğu",
    "ifade",
    "etmektedir",
    "toplumda",
    "birlik",
    "kardeşlik",
    "yardımlaşma",
    "dayanışma",
    "ruhunu",
    "diri",
    "tutan",
    "ibadetin",
    "çerçevesi",
    "kur",
    "kerim",
    "yanı",
    "sıra",
    "peygamber",
    "söz",
    "uygulamalarıyla",
    "belirlenmiştir",
    "hususunda"
  ],
  "search_document": "Başlık: Dişi hayvanların kurban olarak kesilmesinin hükmü nedir? Soru: Dişi hayvanların kurban olarak kesilmesinin hükmü nedir? Cevap: Malî ve sosyal nitelikleri bir arada bulunduran kurban ibadeti, Yüce Allah'a karşı olan teslimiyeti ve kulluğu ifade etmektedir. Toplumda birlik, kardeşlik, yardımlaşma ve dayanışma ruhunu diri tutan bu ibadetin çerçevesi, Kur'an-ı Kerim'in yanı sıra Hz. Peygamber'in (s.a.s.) söz ve uygulamalarıyla belirlenmiştir. Hz. Peygamber'in (s.a.s.) kurban ibadeti hususunda doğrudan veya dolaylı olarak açıklama mahiyetinde birçok söz ve uygulaması olmuştur. Bu söz ve uygulamalara bakıldığında deve, sığır gibi büyükbaş hayvanlarla, koyun, keçi gibi küçükbaş hayvanların belirli şartları taşımaları durumunda, erkek olsun dişi olsun kurban olarak kesildikleri görülmektedir. Ancak İslam âlimleri bu söz ve uygulamalar ışığında kurbanlık hayvanın kesiminde dişi ve erkek cinslerinden hangisinin daha faziletli olduğu hususunda farklı görüşler ortaya koymuşlardır. Mâlikî ve Şafiî mezhebi âlimleri kurbanlık hayvanlarda genel olarak erkek cinsini dişi cinsine göre faziletli görmektedirler. Hanefî mezhebi âlimleri ise koyunda erkek; keçi, deve ve sığırda ise dişi cinslerinin daha faziletli olduğunu ifade etmişlerdir. Ancak her iki görüş sahiplerinin gerekçelerine bakıldığında bunda, yaşadıkları zamanın şartları/ihtiyaçları, hayvanın etinin fazlalığı, lezzeti ve kalitesi ile ilgili değerlendirmelerin ve bölgesel alışkanlıkların etkili olduğu görülmektedir. Nitekim kurbanlıklarda dişi hayvanların kesilmesinin daha faziletli olduğunu ifade eden görüş sahipleri, etinin daha fazla ve kaliteli olacağı gerekçesiyle gerek koyun cinsinden gerekse keçi cinsinden olsun burulmuş olan erkek hayvanın dişisinden daha faziletli olacağını dile getirmişlerdir. Yine kurbanlık hayvanlarda genel olarak erkek cinsinin tercih edilmesini faziletli kabul eden görüş sahipleri, birtakım sebeplerle erkek hayvanın etinin kalitesi düştüğü takdirde, hiç doğum yapmamış dişi hayvanın kurban edilmesinin daha faziletli olacağını belirtmişlerdir (Bkz. Kâsânî, Bedâi, V, 80; Ramlî, Nihâye, VIII, 133; Desukî, Haşiyetü'd-Desukî, II,121; İbn Âbidîn, Reddü'l-Muhtâr, VI, 322; Vehbe Zuhayli, Mevsuatü'lFıkhi'l-İslami ve'l-Kadâya'l-Mu'âsıra, III, 613). Bütün bu görüşler delilleriyle birlikte değerlendirildiğinde bu meseleye genellikle içinde bulunulan şartlar, örf ve alışkanlıklar, etin çokluğu, lezzeti ve kalitesi bağlamında yaklaşıldığı, dolayısıyla konunun ictihadî bir mesele olduğu ortaya çıkmaktadır. Söz konusu bu görüşler, kurban ibadetinin özüyle ve onun değişmez esaslarıyla ilgili olmayıp, toplum menfaatini gözetme ve Yüce Allah'a en iyi hayvanı kurban etme hassasiyetinin bir sonucu olarak sâdır olmuştur. Günümüzde de benzer bir bakış açısıyla farklı görüşlerin ortaya konulması ve farklı tedbirlerin alınması tabiidir. Nitekim benzer tedbirlerin Hz. Peygamber (s.a.s.) döneminde de alındığı görülmektedir. İbn Abbas'ın naklettiğine göre bir dönem develerin azalması üzerine Hz. Peygamber sahabilere sığır kesmelerini emretmişti. (İbn Mâce, \"Edâhî\" 5.) Hz. Peygamber'in (s.a.s.) bu uygulaması, kurbanlık seçiminde, sosyo-ekonomik şartların, kurbanlık hayvanların sayısal ya da niteliksel olarak o andaki özel durumlarının dikkate alınması gerektiğini ve hayvancılık politikası açısından bazı tedbirlerin alınabileceğini göstermesi açısından önem arz etmektedir. Sonuç olarak, kurbanlık hayvanın erkek veya dişi olması, kurbanın geçerlilik şartları arasında yer almamaktadır. Hangisinin kesiminin daha faziletli olduğu hususu ise içinde bulunulan şartlar/ihtiyaçlar, etin çokluğu, lezzeti ve kalitesi bağlamındaki yerleşik örf çerçevesinde tartışılmıştır. Dolayısıyla günümüzde de toplumun menfaati dikkate alınarak hayvan neslinin korunması, dişi hayvanların kurban edilmesinden kaynaklanan maddi kaybın önlenmesi gibi maslahatlar da gözetilerek dişi hayvanların kurban edilmesinin kısıtlanmasında dini bir sakınca bulunmamaktadır. Bu itibarla dişi hayvanların kurban edilmesinin hayvan üretimine zarar vermesi halinde, kurban kesiminde erkek hayvanların tercih edilmesi dinen de uygun olur. Kategori: KURBAN > Kurban Kesmenin Hükmü ve Hikmetleri > Dişi hayvanların kurban olarak kesilmesinin hükmü nedir?",
  "discovered_at": "2026-03-16T23:34:44.715Z",
  "fetched_at": "2026-03-16T23:46:50.056Z",
  "parsed_at": "2026-03-16T23:49:30.731Z",
  "canonical_identifier": "719f8e10-4874-4e23-047d-08dd1c135351",
  "low_confidence": false,
  "decision_kind": null,
  "decision_year": null,
  "decision_no": null,
  "subject": null
}
